classroom_voter/__init__.py
classroom_voter/__main__.py
classroom_voter/admin.py
classroom_voter/client.py
classroom_voter/gui.py
classroom_voter/login.py
classroom_voter/professor.py
classroom_voter/server.py
classroom_voter/serverUtils.py
classroom_voter/shared/__init__.py
classroom_voter/shared/database.py
classroom_voter/shared/encryption_tools.py
classroom_voter/shared/locks.py
classroom_voter/shared/pollTypes.py
classroom_voter/tests/__init__.py
classroom_voter/tests/__main__.py
classroom_voter/tests/test_database.py
classroom_voter/tests/test_polltypes.py
classroom_voter/tests/test_server.py
classroom_voter_harrismcc-0.0.3b1.dist-info/METADATA
classroom_voter_harrismcc-0.0.3b1.dist-info/WHEEL
classroom_voter_harrismcc-0.0.3b1.dist-info/top_level.txt
classroom_voter_harrismcc-0.0.3b1.dist-info/RECORD
