Metadata-Version: 2.1
Name: classroom-voter-harrismcc
Version: 0.0.3b1
Summary: A secure CLI classroom polling system
Home-page: https://github.com/harrismcc/classroom-voter
Author: Harris McCullers, Jay Rodolitz, Douglas Webster, Ishaan Gandhi
Author-email: harrismcc+classroom-voter@gmail.com
License: UNKNOWN
Platform: UNKNOWN
Classifier: Programming Language :: Python :: 3
Classifier: License :: OSI Approved :: MIT License
Classifier: Operating System :: OS Independent
Requires-Python: >=3.6
Requires-Dist: pycryptodome
Requires-Dist: pycryptodomex
